<?xml version="1.0" encoding="GB2312"?>

<tree id="0">
  <item text="内部" id="TT_168">
    <item text="日常报表" id="TT_9">
      <item text="日报" id="TG_1009">
        <item text="徽商银行各分行主要经济指标日报表" id="T_1009_1065"/>
        <item text="徽商银行各分行存款项目分析日报表" id="T_1009_1066"/>
        <item text="徽商银行各分行贷款项目分析日报表" id="T_1009_1067"/>
        <item text="徽商银行各分支行主要经济指标日报表" id="T_1009_1068"/>
        <item text="徽商银行各分支行(存款日均余额)排名一览表" id="T_1009_1073"/>
        <item text="徽商银行各分支行(贷款日均余额)排名一览表" id="T_1009_1074"/>
        <item text="徽商银行存款日均余额报表" id="T_1009_1069"/>
        <item text="徽商银行贷款日均余额报表" id="T_1009_1070"/>
        <item text="徽商银行各支行存款日均余额报表" id="T_1009_1114"/>
        <item text="徽商银行各支行存款日均余额报表" id="T_1009_1071"/>
        <item text="徽商银行各支行贷款日均余额报表" id="T_1009_1072"/>
        <item text="徽商银行各支行贷款日均余额报表" id="T_1009_1115"/>
        <item text="徽商银行各支行(贷款日均余额)排名表" id="T_1009_1113"/>
        <item text="业务及管理费明细表" id="T_1009_1064"/>
      </item>
      <item text="月报" id="TG_1021">
        <item text="徽商银行各分行主要经济指标月报表" id="T_1021_1075"/>
        <item text="存款日均余额变动情况月报表(月)" id="T_1021_1076"/>
        <item text="贷款日均余额变动情况月报表(月)" id="T_1021_1077"/>
      </item>
      <item text="基础报表" id="TG_1022">
        <item text="业务状况表(日报)" id="T_1022_1061"/>
        <item text="业务状况表(旬/月/季/半年/年报)" id="T_1022_1117"/>
        <item text="资产负债表" id="T_1022_1062"/>
        <item text="徽商银行损益明细表" id="T_1022_1063"/>
      </item>
    </item>
    <item text="存贷款分析报表" id="TG_1010">
      <item text="信贷收支月报表" id="T_1010_1078"/>
      <item text="存款类别结构月报表" id="T_1010_1079"/>
      <item text="存款稳定性结构月报" id="T_1010_1081"/>
      <item text="储蓄存款变动情况月报表" id="T_1010_1080"/>
      <item text="贷款余额变动情况月报表" id="T_1010_1082"/>
      <item text="存贷比、不良贷款占比变动情况月报表" id="T_1010_1083"/>
      <item text="存款日均余额变动情况报表" id="T_1010_1084"/>
      <item text="贷款日均余额变动情况报表" id="T_1010_1085"/>
    </item>
    <item text="其他" id="TG_1011">
      <item text="划缴存款旬报表" id="T_1011_1086"/>
      <item text="资产负债比例管理主要指标表" id="T_1011_1087"/>
    </item>
    <item text="财务分析附表" id="TG_1015">
      <item text="各支行经营情况表" id="T_1015_1091"/>
      <item text="营业费用支出情况表" id="T_1015_1092"/>
      <item text="主要财务指标分析表" id="T_1015_1093"/>
      <item text="财务收支计划完成情况表" id="T_1015_1094"/>
    </item>
  </item>
  <item text="向银监局报送" id="TT_6">
    <item text="其他" id="TG_1014">
      <item text="城市商业银行和城市信用社数字快报" id="T_1014_1088"/>
      <item text="银行业金融机构经营情况表" id="T_1014_1089"/>
      <item text="县域经营情况表" id="T_1014_1090"/>
    </item>
    <item text="季度快报" id="TG_1016">
      <item text="城市商业银行季度快报表一：总体经营情况" id="T_1016_1095"/>
      <item text="城市商业银行季度快报表二：贷款质量（一逾两呆）" id="T_1016_1096"/>
      <item text="城市商业银行季度快报表三：监控指标" id="T_1016_1097"/>
      <item text="城市商业银行季度快报表四：应收应付项目" id="T_1016_1098"/>
      <item text="城市商业银行季度快报表五：其他资产负债" id="T_1016_1099"/>
    </item>
    <item text="非现场监管" id="TG_1017">
      <item text="备付金比例指标报表" id="T_1017_1100"/>
      <item text="存贷款比例指标报表" id="T_1017_1101"/>
      <item text="中长期贷款比例指标报表" id="T_1017_1102"/>
      <item text="监测性指标报表" id="T_1017_1103"/>
      <item text="贷款质量指标报表" id="T_1017_1104"/>
    </item>
    <item text="季度快报补充" id="TG_1018">
      <item text="季度快报补充报表一（总体经营情况表）" id="T_1018_1105"/>
      <item text="城市商业银行资产负债比例监控指标汇总表" id="T_1018_1106"/>
      <item text="季度快报补充报表三汇总型（贷款质量分析表）" id="T_1018_1107"/>
      <item text="季度快报补充报表四（资产负债结构分析表）" id="T_1018_1108"/>
      <item text="季度快报补充报表五（损益分析表）" id="T_1018_1109"/>
      <item text="季度快报补充报表六（资产负债比例计算补充报表）" id="T_1018_1112"/>
    </item>
  </item>
  <item text="向人行报送" id="TT_7">
    <item text="人行会计科" id="TG_1019">
      <item text="商业银行主要经营指标分析表（一）" id="T_1019_1110"/>
      <item text="商业银行主要经营指标分析表（二）" id="T_1019_1111"/>
    </item>
  </item>
</tree>
